[
  {
    "company": "Cadence Design Systems",
    "title": "Application Engineer - Physical Design (Back-End)",
    "location": "2 Locations",
    "url": "https://cadence.wd1.myworkdayjobs.com/job/PETAH-TIKVA/Application-Engineer---Physical-Design--Back-End-_R54943"
  },
  {
    "company": "Cadence Design Systems",
    "title": "Application Engineer - Physical Design (Back-End)",
    "location": "PETAH TIKVA",
    "url": "https://cadence.wd1.myworkdayjobs.com/job/PETAH-TIKVA/Application-Engineer---Physical-Design--Back-End-_R54944"
  },
  {
    "company": "Cadence Design Systems",
    "title": "Software Engineer II",
    "location": "SAN JOSE",
    "url": "https://cadence.wd1.myworkdayjobs.com/job/SAN-JOSE/Software-Engineer-II_R52336-2"
  },
  {
    "company": "Cadence Design Systems",
    "title": "Software Engineer II - AI Focused",
    "location": "BELO HORIZONTE",
    "url": "https://cadence.wd1.myworkdayjobs.com/job/BELO-HORIZONTE/Software-Engineer-II---AI-Focused_R54711"
  },
  {
    "company": "Cadence Design Systems",
    "title": "Software Engineer II : AI Compiler Engineer",
    "location": "BELO HORIZONTE",
    "url": "https://cadence.wd1.myworkdayjobs.com/job/BELO-HORIZONTE/Software-Engineer-II---AI-Compiler-Engineer_R54898"
  },
  {
    "company": "Cadence Design Systems",
    "title": "Software Engineer II, AI Platform",
    "location": "SAN JOSE",
    "url": "https://cadence.wd1.myworkdayjobs.com/job/SAN-JOSE/Software-Engineer-II--AI-Platform_R55030-1"
  },
  {
    "company": "Diconium digital solutions GmbH",
    "title": "Backend Developer (all genders)",
    "location": "2 Locations",
    "url": "https://diconium.wd3.myworkdayjobs.com/job/Lisbon/Backend-Developer--all-genders-_JR100443"
  },
  {
    "company": "Etsy",
    "title": "Software Engineer II, Machine Learning, Risk Engineering Brooklyn, Brooklyn Heights, New York, United States, 11201 Data Science & Machine Learning",
    "location": "Unknown",
    "url": "https://careers.etsy.com/jobs/software-engineer-ii-machine-learning-risk-engineering-brooklyn-new-york-united-states"
  },
  {
    "company": "Nvidia",
    "title": "Physical Design Backend Engineer",
    "location": "Israel, Yokneam",
    "url": "https://nvidia.wd5.myworkdayjobs.com/job/Israel-Yokneam/Physical-Design-Backend-Engineer_JR2015705"
  }
]